__init__.py
pykingenie/__init__.py
pykingenie/fitter.py
pykingenie/fitter_solution.py
pykingenie/fitter_surface.py
pykingenie/gator.py
pykingenie/kingenie_solution.py
pykingenie/kingenie_surface.py
pykingenie/main.py
pykingenie/octet.py
pykingenie/solution_exp.py
pykingenie/surface_exp.py
pykingenie/utils/__init__.py
pykingenie/utils/fitting_general.py
pykingenie/utils/fitting_solution.py
pykingenie/utils/fitting_surface.py
pykingenie/utils/math.py
pykingenie/utils/palettes.py
pykingenie/utils/plotting.py
pykingenie/utils/processing.py
pykingenie/utils/signal_solution.py
pykingenie/utils/signal_surface.py
pykingenie-0.1.8.dist-info/licenses/LICENSE
pykingenie-0.1.8.dist-info/METADATA
pykingenie-0.1.8.dist-info/WHEEL
pykingenie-0.1.8.dist-info/top_level.txt
pykingenie-0.1.8.dist-info/RECORD
