Metadata-Version: 2.4
Name: pykingenie
Version: 0.1.8
Author-email: Osvaldo Burastero <oburastero@gmail.com>
License: MIT
Requires-Python: >=3.10
License-File: LICENSE
Requires-Dist: plotly>=6.2.0
Requires-Dist: kaleido>=1.0.0
Requires-Dist: numpy>=2.2.5
Requires-Dist: pandas>=2.2.3
Requires-Dist: scipy>=1.15.2
Requires-Dist: matplotlib>=3.10.1
Provides-Extra: dev
Requires-Dist: black>=25.1.0; extra == "dev"
Requires-Dist: coverage-badge>=1.1.2; extra == "dev"
Requires-Dist: flake8>=7.3.0; extra == "dev"
Requires-Dist: ipykernel>=6.30.0; extra == "dev"
Requires-Dist: jupyter>=1.1.1; extra == "dev"
Requires-Dist: notebook>=7.4.4; extra == "dev"
Requires-Dist: numpydoc>=1.9.0; extra == "dev"
Requires-Dist: pydata-sphinx-theme>=0.16.1; extra == "dev"
Requires-Dist: pytest>=8.4.1; extra == "dev"
Requires-Dist: pytest-cov>=6.2.1; extra == "dev"
Requires-Dist: sphinx>=8.1.3; extra == "dev"
Requires-Dist: sphinx-copybutton>=0.5.2; extra == "dev"
Requires-Dist: sphinx-design>=0.6.1; extra == "dev"
Requires-Dist: sphinx-tabs>=3.4.7; extra == "dev"
Provides-Extra: docs
Requires-Dist: numpydoc>=1.9.0; extra == "docs"
Requires-Dist: pydata-sphinx-theme>=0.16.1; extra == "docs"
Requires-Dist: sphinx>=8.1.3; extra == "docs"
Requires-Dist: sphinx-copybutton>=0.5.2; extra == "docs"
Requires-Dist: sphinx-design>=0.6.1; extra == "docs"
Requires-Dist: sphinx-tabs>=3.4.7; extra == "docs"
Provides-Extra: test
Requires-Dist: pytest>=8.4.1; extra == "test"
Requires-Dist: pytest-cov>=6.2.1; extra == "test"
Dynamic: license-file
